TracProjectMenu-2.0.dist-info/DESCRIPTION.rst
TracProjectMenu-2.0.dist-info/METADATA
TracProjectMenu-2.0.dist-info/RECORD
TracProjectMenu-2.0.dist-info/WHEEL
TracProjectMenu-2.0.dist-info/entry_points.txt
TracProjectMenu-2.0.dist-info/metadata.json
TracProjectMenu-2.0.dist-info/top_level.txt
projectmenu/__init__.py
projectmenu/web_ui.py
projectmenu/htdocs/projectmenu.js
