Metadata-Version: 2.0
Name: TracProjectMenu
Version: 2.0
Summary: Provide a menu entry to switch between projects in TRAC_ENV_PARENT_DIR-type setup.
Home-page: http://trac-hacks.org/wiki/ProjectMenuPlugin
Author: Noah Kantrowitz
Author-email: noah@coderanger.net
License: 3-Clause BSD
Keywords: trac plugin multiproject
Platform: UNKNOWN
Classifier: Framework :: Trac
